tests/__init__.py
tests/test_TimeAxisBuilder.py
tests/test_timeAxis.py
tests/test_timeAxisBinding.py
tests/test_timeAxisConverter.py
tests/test_timeInterval.py
timeaxis/__init__.py
timeaxis/_version.py
timeaxis/timeaxisbinding.py
timeaxis/timeaxisconverter.py
timeaxis/timeaxiscore.py
TimeAxis-19.11.7.59750.dist-info/LICENSE
TimeAxis-19.11.7.59750.dist-info/METADATA
TimeAxis-19.11.7.59750.dist-info/WHEEL
TimeAxis-19.11.7.59750.dist-info/top_level.txt
TimeAxis-19.11.7.59750.dist-info/RECORD
