Metadata-Version: 2.1
Name: TimeAxis
Version: 19.11.7.59750
Summary: UNKNOWN
Home-page: https://github.com/maboualidev/TimeAxis
Author: Mohammad ABouali
Author-email: maboualidev@gmail.com
License: UNKNOWN
Platform: UNKNOWN
Classifier: Programming Language :: Python :: 3
Classifier: Operating System :: OS Independent
Requires-Python: >=3.7
Requires-Dist: numpy
Requires-Dist: cftime
Requires-Dist: scipy
Requires-Dist: numba
